xcp/__init__.py
xcp/client.py
xcp/daq.py
xcp/protocol.py
xcp/server.py
xcp/transport.py
socketcan_xcp-0.0.2.dist-info/LICENSE
socketcan_xcp-0.0.2.dist-info/METADATA
socketcan_xcp-0.0.2.dist-info/WHEEL
socketcan_xcp-0.0.2.dist-info/top_level.txt
socketcan_xcp-0.0.2.dist-info/RECORD
