Metadata-Version: 2.1
Name: socketcan-xcp
Version: 0.0.2
Summary: A python 3 interface to Universal Measurement and Calibration Protocol XCP
Home-page: https://gitlab.com/menschel/socketcan-xcp
Author: Patrick Menschel
Author-email: menschel.p@posteo.de
Keywords: socketcan can xcp
Classifier: Development Status :: 4 - Beta
Classifier: Programming Language :: Python :: 3 :: Only
Classifier: License :: OSI Approved :: GNU General Public License v3 or later (GPLv3+)
Classifier: Operating System :: POSIX :: Linux
Classifier: Intended Audience :: Developers
Classifier: Topic :: Scientific/Engineering
Classifier: Topic :: Software Development :: Embedded Systems
Requires: socketcan
Requires-Python: >=3.9
License-File: LICENSE
